chipheures_sos/__init__.py
chipheures_sos/app.py
chipheures_sos/cli.py
chipheures_sos/db.py
chipheures_sos/model/__init__.py
chipheures_sos/model/oder.py
ChipHeures_SOS-20.0.0.dist-info/LICENSE.rst
ChipHeures_SOS-20.0.0.dist-info/METADATA
ChipHeures_SOS-20.0.0.dist-info/WHEEL
ChipHeures_SOS-20.0.0.dist-info/entry_points.txt
ChipHeures_SOS-20.0.0.dist-info/top_level.txt
ChipHeures_SOS-20.0.0.dist-info/RECORD
