Metadata-Version: 2.1
Name: ChipHeures-SOS
Version: 20.0.0
Summary: Tool for database maintenance of the Chip'heures web application
Home-page: UNKNOWN
Author: Laurent LAPORTE
Author-email: tantale.solutions@gmail.com
License: MIT
Keywords: database,sqlite,maintenant,intranet,web,application
Platform: posix
Platform: nt
Classifier: Development Status :: 5 - Production/Stable
Classifier: Intended Audience :: Developers
Classifier: Operating System :: Unix
Classifier: Operating System :: POSIX
Classifier: Operating System :: Microsoft :: Windows
Classifier: Programming Language :: Python
Classifier: Programming Language :: Python :: 2.7
Classifier: Topic :: Utilities
Requires-Python: >=2.7, <3
Requires-Dist: Click
Provides-Extra: test
